digitales2/alu.v
module alu (
    input wire [31:0] a,
    input wire [31:0] b,
    input wire [2:0] op,
    output wire [31:0] ALU_out
);

assign ALU_out =
    (op == 3'b000) ? a + b :
    (op == 3'b001) ? a - b :
    (op == 3'b010) ? a & b :
    (op == 3'b011) ? a | b :
                     a ^ b;

endmodule

digitales2/registerfile.v
module registerfile(
    input  wire        clk,          // Señal de reloj
    input  wire        wr_en,        // Habilitación de escritura
    input  wire [4:0]  wr_index,     // Dirección de escritura
    input  wire [31:0] wr_data,      // Dato a escribir

    input  wire [4:0]  rd_index1,    // Dirección de lectura 1
    input  wire [4:0]  rd_index2,    // Dirección de lectura 2

    output wire [31:0] rd_data1,     // Dato leído 1
    output wire [31:0] rd_data2      // Dato leído 2
);

    // Banco de registros: 32 registros de 32 bits
    reg [31:0] RF [0:31];

    integer i;

    // Inicialización (solo simulación)
    initial begin
        for (i = 0; i < 32; i = i + 1)
            RF[i] = 32'd0;
    end

    // Escritura síncrona
    always @(posedge clk) begin
        if (wr_en && (wr_index != 5'd0))
            RF[wr_index] <= wr_data;

        // x0 siempre vale cero
        RF[0] <= 32'd0;
    end

    // Lecturas
    assign rd_data1 = (rd_index1 == 5'd0) ? 32'd0 : RF[rd_index1];
    assign rd_data2 = (rd_index2 == 5'd0) ? 32'd0 : RF[rd_index2];

endmodule

digitales2/riscv.v
module riscv (
    input wire clk,
    input wire rst,
    input wire [31:0] instr
);

    // ------------------------------------------------
    // REGISTRO DE INSTRUCCIÓN
    // ------------------------------------------------

    reg [31:0] IR;

    always @(posedge clk) begin
        IR <= instr;
    end


    // ------------------------------------------------
    // CAMPOS DE LA INSTRUCCIÓN TIPO R
    // ------------------------------------------------

    wire [6:0] funct7;
    wire [4:0] rs2;
    wire [4:0] rs1;
    wire [2:0] funct3;
    wire [4:0] rd;
    wire [6:0] opcode;

    assign funct7 = IR[31:25];
    assign rs2    = IR[24:20];
    assign rs1    = IR[19:15];
    assign funct3 = IR[14:12];
    assign rd     = IR[11:7];
    assign opcode = IR[6:0];


    // ------------------------------------------------
    // SEÑALES DEL REGISTER FILE
    // ------------------------------------------------

    wire [31:0] src1_value;
    wire [31:0] src2_value;

    wire [31:0] alu_a;
    wire [31:0] alu_b;
    wire [31:0] alu_out;


    // ------------------------------------------------
    // DECODIFICACIÓN DE INSTRUCCIONES
    // ------------------------------------------------

    wire [10:0] dec_bits;

    wire is_add;
    wire is_sub;
    wire is_and;
    wire is_or;
    wire is_xor;

    assign dec_bits = {funct7[5], funct3, opcode};

    // ADD
    assign is_add = (dec_bits == 11'b0_000_0110011);

    // SUB
    assign is_sub = (dec_bits == 11'b1_000_0110011);

    // AND
    assign is_and = (dec_bits == 11'b0_111_0110011);

    // OR
    assign is_or = (dec_bits == 11'b0_110_0110011);

    // XOR
    assign is_xor = (dec_bits == 11'b0_100_0110011);


    // ------------------------------------------------
    // HABILITACIÓN DE ESCRITURA
    // ------------------------------------------------

    wire wr_en;

    assign wr_en = is_add |
                   is_sub |
                   is_and |
                   is_or  |
                   is_xor;


    // ------------------------------------------------
    // REGISTER FILE
    // ------------------------------------------------

    registerfile rf (
        .clk(clk),
        .wr_en(wr_en),
        .wr_index(rd),
        .wr_data(alu_out),

        .rd_index1(rs1),
        .rd_data1(src1_value),

        .rd_index2(rs2),
        .rd_data2(src2_value)
    );


    // ------------------------------------------------
    // ENTRADAS DE LA ALU
    // ------------------------------------------------

    assign alu_a = src1_value;
    assign alu_b = src2_value;


    // ------------------------------------------------
    // ALU
    // ------------------------------------------------

    alu rv_alu (
        .a(alu_a),
        .b(alu_b),

        .op(
            is_add ? 3'b000 :
            is_sub ? 3'b001 :
            is_and ? 3'b010 :
            is_or  ? 3'b011 :
                     3'b100
        ),

        .ALU_out(alu_out)
    );

endmodule

digitales2/riscv_tb.v
`timescale 1ns/1ps

module tb_riscv;

    // Señales de prueba
    reg [31:0] instr;
    reg clk;
    reg rst;

    // Instancia del procesador
    riscv uut (
        .clk(clk),
        .rst(rst),
        .instr(instr)
    );

    integer i;

    initial begin

        // Archivo de simulación
        $dumpfile("tb_riscv.vcd");
        $dumpvars(0, tb_riscv);

        // Guardar todos los registros
        for (i = 0; i < 32; i = i + 1)
            $dumpvars(0, uut.rf.RF[i]);

        // Inicializar los registros
        // xN = N
        for (i = 0; i < 32; i = i + 1)
            uut.rf.RF[i] = i;

        // Mostrar registros importantes
        $monitor($time,
                 " clk=%d | instr=%h | x4=%h | x5=%h | x6=%h | x7=%h | x8=%h",
                 clk,
                 instr,
                 uut.rf.RF[4],
                 uut.rf.RF[5],
                 uut.rf.RF[6],
                 uut.rf.RF[7],
                 uut.rf.RF[8]);

        // Estado inicial
        #0;
        clk = 0;
        rst = 1;
        instr = 32'b0;

        // Liberar reset
        #3;
        rst = 0;


        // ------------------------------------------------
        // PRUEBA 1: ADD
        // x4 = x3 + x2
        // x4 = 3 + 2 = 5
        // ------------------------------------------------

        instr = 32'b0000000_00010_00011_000_00100_0110011;
        $display("ADD x4, x3, x2");

        #12;


        // ------------------------------------------------
        // PRUEBA 2: SUB
        // x5 = x3 - x2
        // x5 = 3 - 2 = 1
        // ------------------------------------------------

        instr = 32'b0100000_00010_00011_000_00101_0110011;
        $display("SUB x5, x3, x2");

        #12;


        // ------------------------------------------------
        // PRUEBA 3: AND
        // x6 = x10 & x12
        // 10 & 12 = 8
        // ------------------------------------------------

        instr = 32'b0000000_01100_01010_111_00110_0110011;
        $display("AND x6, x10, x12");

        #12;


        // ------------------------------------------------
        // PRUEBA 4: OR
        // x8 = x10 | x12
        // 10 | 12 = 14
        // ------------------------------------------------

        instr = 32'b0000000_01100_01010_110_01000_0110011;
        $display("OR x8, x10, x12");

        #12;


        // ------------------------------------------------
        // PRUEBA 5: XOR
        // x7 = x10 ^ x12
        // 10 ^ 12 = 6
        // ------------------------------------------------

        instr = 32'b0000000_01100_01010_100_00111_0110011;
        $display("XOR x7, x10, x12");

        #16;


        // Fin de la simulación
        $finish;

    end


    // Generador de reloj
    always begin
        #2 clk = ~clk;
    end

endmodule

digitales2/tb_riscv.vcd
$date
	Sat Sep 12 05:20:22 2026
$end
$version
	Icarus Verilog
$end
$timescale
	1ps
$end
$scope module tb_riscv $end
$var reg 1 ! clk $end
$var reg 32 " instr [31:0] $end
$var reg 1 # rst $end
$var integer 32 $ i [31:0] $end
$scope module uut $end
$var wire 32 % alu_a [31:0] $end
$var wire 32 & alu_b [31:0] $end
$var wire 1 ! clk $end
$var wire 32 ' instr [31:0] $end
$var wire 1 # rst $end
$var wire 1 ( wr_en $end
$var wire 32 ) src2_value [31:0] $end
$var wire 32 * src1_value [31:0] $end
$var wire 5 + rs2 [4:0] $end
$var wire 5 , rs1 [4:0] $end
$var wire 5 - rd [4:0] $end
$var wire 7 . opcode [6:0] $end
$var wire 1 / is_xor $end
$var wire 1 0 is_sub $end
$var wire 1 1 is_or $end
$var wire 1 2 is_and $end
$var wire 1 3 is_add $end
$var wire 7 4 funct7 [6:0] $end
$var wire 3 5 funct3 [2:0] $end
$var wire 11 6 dec_bits [10:0] $end
$var wire 32 7 alu_out [31:0] $end
$var reg 32 8 IR [31:0] $end
$scope module rf $end
$var wire 1 ! clk $end
$var wire 5 9 rd_index1 [4:0] $end
$var wire 5 : rd_index2 [4:0] $end
$var wire 1 ( wr_en $end
$var wire 5 ; wr_index [4:0] $end
$var wire 32 < wr_data [31:0] $end
$var wire 32 = rd_data2 [31:0] $end
$var wire 32 > rd_data1 [31:0] $end
$var integer 32 ? i [31:0] $end
$upscope $end
$scope module rv_alu $end
$var wire 32 @ a [31:0] $end
$var wire 32 A b [31:0] $end
$var wire 3 B op [2:0] $end
$var wire 32 C ALU_out [31:0] $end
$upscope $end
$upscope $end
$upscope $end
$scope module tb_riscv $end
$scope module uut $end
$scope module rf $end
$var reg 32 D \RF[0] [31:0] $end
$upscope $end
$upscope $end
$upscope $end
$scope module tb_riscv $end
$scope module uut $end
$scope module rf $end
$var reg 32 E \RF[1] [31:0] $end
$upscope $end
$upscope $end
$upscope $end
$scope module tb_riscv $end
$scope module uut $end
$scope module rf $end
$var reg 32 F \RF[2] [31:0] $end
$upscope $end
$upscope $end
$upscope $end
$scope module tb_riscv $end
$scope module uut $end
$scope module rf $end
$var reg 32 G \RF[3] [31:0] $end
$upscope $end
$upscope $end
$upscope $end
$scope module tb_riscv $end
$scope module uut $end
$scope module rf $end
$var reg 32 H \RF[4] [31:0] $end
$upscope $end
$upscope $end
$upscope $end
$scope module tb_riscv $end
$scope module uut $end
$scope module rf $end
$var reg 32 I \RF[5] [31:0] $end
$upscope $end
$upscope $end
$upscope $end
$scope module tb_riscv $end
$scope module uut $end
$scope module rf $end
$var reg 32 J \RF[6] [31:0] $end
$upscope $end
$upscope $end
$upscope $end
$scope module tb_riscv $end
$scope module uut $end
$scope module rf $end
$var reg 32 K \RF[7] [31:0] $end
$upscope $end
$upscope $end
$upscope $end
$scope module tb_riscv $end
$scope module uut $end
$scope module rf $end
$var reg 32 L \RF[8] [31:0] $end
$upscope $end
$upscope $end
$upscope $end
$scope module tb_riscv $end
$scope module uut $end
$scope module rf $end
$var reg 32 M \RF[9] [31:0] $end
$upscope $end
$upscope $end
$upscope $end
$scope module tb_riscv $end
$scope module uut $end
$scope module rf $end
$var reg 32 N \RF[10] [31:0] $end
$upscope $end
$upscope $end
$upscope $end
$scope module tb_riscv $end
$scope module uut $end
$scope module rf $end
$var reg 32 O \RF[11] [31:0] $end
$upscope $end
$upscope $end
$upscope $end
$scope module tb_riscv $end
$scope module uut $end
$scope module rf $end
$var reg 32 P \RF[12] [31:0] $end
$upscope $end
$upscope $end
$upscope $end
$scope module tb_riscv $end
$scope module uut $end
$scope module rf $end
$var reg 32 Q \RF[13] [31:0] $end
$upscope $end
$upscope $end
$upscope $end
$scope module tb_riscv $end
$scope module uut $end
$scope module rf $end
$var reg 32 R \RF[14] [31:0] $end
$upscope $end
$upscope $end
$upscope $end
$scope module tb_riscv $end
$scope module uut $end
$scope module rf $end
$var reg 32 S \RF[15] [31:0] $end
$upscope $end
$upscope $end
$upscope $end
$scope module tb_riscv $end
$scope module uut $end
$scope module rf $end
$var reg 32 T \RF[16] [31:0] $end
$upscope $end
$upscope $end
$upscope $end
$scope module tb_riscv $end
$scope module uut $end
$scope module rf $end
$var reg 32 U \RF[17] [31:0] $end
$upscope $end
$upscope $end
$upscope $end
$scope module tb_riscv $end
$scope module uut $end
$scope module rf $end
$var reg 32 V \RF[18] [31:0] $end
$upscope $end
$upscope $end
$upscope $end
$scope module tb_riscv $end
$scope module uut $end
$scope module rf $end
$var reg 32 W \RF[19] [31:0] $end
$upscope $end
$upscope $end
$upscope $end
$scope module tb_riscv $end
$scope module uut $end
$scope module rf $end
$var reg 32 X \RF[20] [31:0] $end
$upscope $end
$upscope $end
$upscope $end
$scope module tb_riscv $end
$scope module uut $end
$scope module rf $end
$var reg 32 Y \RF[21] [31:0] $end
$upscope $end
$upscope $end
$upscope $end
$scope module tb_riscv $end
$scope module uut $end
$scope module rf $end
$var reg 32 Z \RF[22] [31:0] $end
$upscope $end
$upscope $end
$upscope $end
$scope module tb_riscv $end
$scope module uut $end
$scope module rf $end
$var reg 32 [ \RF[23] [31:0] $end
$upscope $end
$upscope $end
$upscope $end
$scope module tb_riscv $end
$scope module uut $end
$scope module rf $end
$var reg 32 \ \RF[24] [31:0] $end
$upscope $end
$upscope $end
$upscope $end
$scope module tb_riscv $end
$scope module uut $end
$scope module rf $end
$var reg 32 ] \RF[25] [31:0] $end
$upscope $end
$upscope $end
$upscope $end
$scope module tb_riscv $end
$scope module uut $end
$scope module rf $end
$var reg 32 ^ \RF[26] [31:0] $end
$upscope $end
$upscope $end
$upscope $end
$scope module tb_riscv $end
$scope module uut $end
$scope module rf $end
$var reg 32 _ \RF[27] [31:0] $end
$upscope $end
$upscope $end
$upscope $end
$scope module tb_riscv $end
$scope module uut $end
$scope module rf $end
$var reg 32 ` \RF[28] [31:0] $end
$upscope $end
$upscope $end
$upscope $end
$scope module tb_riscv $end
$scope module uut $end
$scope module rf $end
$var reg 32 a \RF[29] [31:0] $end
$upscope $end
$upscope $end
$upscope $end
$scope module tb_riscv $end
$scope module uut $end
$scope module rf $end
$var reg 32 b \RF[30] [31:0] $end
$upscope $end
$upscope $end
$upscope $end
$scope module tb_riscv $end
$scope module uut $end
$scope module rf $end
$var reg 32 c \RF[31] [31:0] $end
$upscope $end
$upscope $end
$upscope $end
$enddefinitions $end
$comment Show the parameter values. $end
$dumpall
$end
#0
$dumpvars
b11111 c
b11110 b
b11101 a
b11100 `
b11011 _
b11010 ^
b11001 ]
b11000 \
b10111 [
b10110 Z
b10101 Y
b10100 X
b10011 W
b10010 V
b10001 U
b10000 T
b1111 S
b1110 R
b1101 Q
b1100 P
b1011 O
b1010 N
b1001 M
b1000 L
b111 K
b110 J
b101 I
b100 H
b11 G
b10 F
b1 E
b0 D
bx C
bx B
bx A
bx @
b100000 ?
bx >
bx =
bx <
bx ;
bx :
bx 9
bx 8
bx 7
bx 6
bx 5
bx 4
x3
x2
x1
x0
x/
bx .
bx -
bx ,
bx +
bx *
bx )
x(
b0 '
bx &
bx %
b100000 $
1#
b0 "
0!
$end
#2000
b0 7
b0 <
b0 C
0(
b100 B
b0 &
b0 A
b0 )
b0 =
b0 %
b0 @
b0 *
b0 >
03
00
02
01
0/
b0 6
b0 4
b0 +
b0 :
b0 ,
b0 9
b0 5
b0 -
b0 ;
b0 .
b0 D
b0 8
1!
#3000
b1000011000001000110011 "
b1000011000001000110011 '
0#
#4000
0!
#6000
1(
b101 7
b101 <
b101 C
b0 B
b10 &
b10 A
b10 )
b10 =
b11 %
b11 @
b11 *
b11 >
13
b110011 6
b10 +
b10 :
b11 ,
b11 9
b100 -
b100 ;
b110011 .
b1000011000001000110011 8
b0 D
1!
#8000
0!
#10000
b0 D
b101 H
1!
#12000
0!
#14000
b0 D
b101 H
1!
#15000
b1000000001000011000001010110011 "
b1000000001000011000001010110011 '
#16000
0!
#18000
b1 7
b1 <
b1 C
b1 B
03
10
b10000110011 6
b100000 4
b101 -
b101 ;
b0 D
b101 H
b1000000001000011000001010110011 8
1!
#20000
0!
#22000
b0 D
b1 I
1!
#24000
0!
#26000
b0 D
b1 I
1!
#27000
b110001010111001100110011 "
b110001010111001100110011 '
#28000
0!
#30000
b1000 7
b1000 <
b1000 C
b10 B
12
b1100 &
b1100 A
b1100 )
b1100 =
b1010 %
b1010 @
b1010 *
b1010 >
00
b1110110011 6
b0 4
b1100 +
b1100 :
b1010 ,
b1010 9
b111 5
b110 -
b110 ;
b110001010111001100110011 8
b0 D
b1 I
1!
#32000
0!
#34000
b0 D
b1000 J
1!
#36000
0!
#38000
b0 D
b1000 J
1!
#39000
b110001010110010000110011 "
b110001010110010000110011 '
#40000
0!
#42000
b1110 7
b1110 <
b1110 C
b11 B
02
11
b1100110011 6
b110 5
b1000 -
b1000 ;
b0 D
b1000 J
b110001010110010000110011 8
1!
#44000
0!
#46000
b0 D
b1110 L
1!
#48000
0!
#50000
b0 D
b1110 L
1!
#51000
b110001010100001110110011 "
b110001010100001110110011 '
#52000
0!
#54000
b110 7
b110 <
b110 C
b100 B
01
1/
b1000110011 6
b100 5
b111 -
b111 ;
b110001010100001110110011 8
b0 D
b1110 L
1!
#56000
0!
#58000
b0 D
b110 K
1!
#60000
0!
#62000
b0 D
b110 K
1!
#64000
0!
#66000
b0 D
b110 K
1!
