digitales2/digitales2/mcu.v
`timescale 1ns / 1ps

// Definición del microcontrolador (Plantilla exactas líneas 2-37 del laboratorio)
module mcu (
    input clk, // Reloj del microcontrolador
    input rst  // Reset del microcontrolador
);

    // Buses con la memoria de programa (IMEM)
    wire [31:0] instr; // Instrucción de entrada
    wire [31:0] iaddr; // Dirección en la IMEM

    // Buses con la memoria de datos (DMEM)
    wire [31:0] daddr;    // Dirección en la DMEM
    wire [31:0] ddata_in; // Bus de datos DMEM (entrada)
    wire [31:0] ddata_out;// Bus de datos DMEM (salida)
    wire dwr_en;          // Señales del bus de control DMEM
    wire drd_en;

    // Instancia del microprocesador RISCV
    riscv cpu (
        .rst(rst),
        .clk(clk),
        .instr(instr),
        .iaddr(iaddr),
        .daddr(daddr),
        .ddata_in(ddata_in),
        .ddata_out(ddata_out),
        .dwr_en(dwr_en),
        .drd_en(drd_en)
    );

    // Instancia de la memoria de programa
    rom4096x32 IMEM (
        .data(instr),
        .addr(iaddr[13:2])
    );

endmodule


// Declaración de la memoria ROM de programa (Plantilla líneas 41-45 + Programa do..while)
module rom4096x32 (
    input wire [11:0] addr,  // Dirección de 12 bits (4096 palabras de 32 bits)
    output reg [31:0] data   // Datos/Instrucción de 32 bits
);

    always @(*) begin
        case (addr)
            12'd0: data = 32'h000001B3; // add x3, x0, x0
            12'd1: data = 32'h000002B3; // add x5, x0, x0
            12'd2: data = 32'h00500313; // addi x6, x0, 5
            12'd3: data = 32'h005281B3; // do1: add x3, x3, x5
            12'd4: data = 32'h00128293; // addi x5, x5, 1
            12'd5: data = 32'hFE62CCE3; // blt x5, x6, do1 (salto relativo hacia atrás)
            12'd6: data = 32'h00018613; // finwhile: add x12, x3, x0
            default: data = 32'h00000013; // NOP (addi x0, x0, 0)
        endcase
    end

endmodule

digitales2/alu.v
module alu (
    input wire [31:0] a,
    input wire [31:0] b,
    input wire [2:0] op,
    output wire [31:0] ALU_out
);

assign ALU_out =
    (op == 3'b000) ? a + b :
    (op == 3'b001) ? a - b :
    (op == 3'b010) ? a & b :
    (op == 3'b011) ? a | b :
                     a ^ b;

endmodule

digitales2/digitales2/registerfile.v
module registerfile(
    input  wire        clk,
    input  wire        wr_en,
    input  wire [4:0]  wr_index,
    input  wire [31:0] wr_data,

    input  wire [4:0]  rd_index1,
    input  wire [4:0]  rd_index2,

    output wire [31:0] rd_data1,
    output wire [31:0] rd_data2
);

    // Banco de 32 registros de 32 bits
    reg [31:0] RF [0:31];

    integer i;

    // Inicialización para simulación
    initial begin
        for (i = 0; i < 32; i = i + 1)
            RF[i] = 32'd0;
    end

    // Escritura síncrona
    always @(posedge clk) begin
        if (wr_en && (wr_index != 5'd0))
            RF[wr_index] <= wr_data;

        // x0 siempre permanece en cero
        RF[0] <= 32'd0;
    end

    // Lectura combinacional
    assign rd_data1 = (rd_index1 == 5'd0) ? 32'd0 : RF[rd_index1];
    assign rd_data2 = (rd_index2 == 5'd0) ? 32'd0 : RF[rd_index2];

endmodule

digitales2/digitales2/riscv.v
`timescale 1ns/1ps

module riscv (
    input wire clk,
    input wire rst,
    input wire [31:0] instr,
    output wire [31:0] iaddr,
    output wire [31:0] daddr,
    output wire [31:0] ddata_out,
    input wire [31:0] ddata_in,
    output wire dwr_en,
    output wire drd_en
);

    // Asignaciones temporales para la memoria de datos (DMEM)
    assign daddr     = 32'b0;
    assign ddata_out = 32'b0;
    assign dwr_en    = 1'b0;
    assign drd_en    = 1'b0;

    // ----------------------------------------------------
    // C) UNIDAD DE FETCH Y CICLO DE INSTRUCCIÓN (3 ESTADOS)
    // ----------------------------------------------------
    reg [31:0] pc; // Contador de programa

    // Conecta el PC al bus de direcciones de la IMEM
    assign iaddr = pc;

    // Contador en anillo para los estados
    reg state_fetch, state_decode, state_execute;

    always @(negedge clk) begin
        if (rst) begin
            state_fetch   <= 1'b1;
            state_decode  <= 1'b0;
            state_execute <= 1'b0;
        end else begin
            state_fetch   <= state_execute;
            state_decode  <= state_fetch;
            state_execute <= state_decode;
        end
    end

    // Registro de instrucción (IR)
    reg [31:0] IR; 
    always @(posedge clk) begin
        if (rst)
            IR <= 32'd0;
        else if (state_fetch)
            IR <= instr; // Captura en la fase FETCH
    end

    // ----------------------------------------------------
    // DECODIFICACIÓN DE CAMPOS
    // ----------------------------------------------------
    wire [6:0] funct7 = IR[31:25];
    wire [4:0] rs2    = IR[24:20];
    wire [4:0] rs1    = IR[19:15];
    wire [2:0] funct3 = IR[14:12];
    wire [4:0] rd     = IR[11:7];
    wire [6:0] opcode = IR[6:0];

    // Validación de bits [1:0]
    wire is_valid = (opcode[1:0] == 2'b11);

    // Detección por opcode[6:2]
    wire is_i_instr = is_valid && (
                        (opcode[6:2] == 5'b00000) || 
                        (opcode[6:2] == 5'b00001) || 
                        (opcode[6:2] == 5'b00100) || 
                        (opcode[6:2] == 5'b11001)
                      );

    wire is_r_instr = is_valid && (
                        (opcode[6:2] == 5'b01100) || 
                        (opcode[6:2] == 5'b01101) || 
                        (opcode[6:2] == 5'b10100)
                      );

    wire is_s_instr = is_valid && ((opcode[6:2] == 5'b01000) || (opcode[6:2] == 5'b01001));
    wire is_b_instr = is_valid && (opcode[6:2] == 5'b11000);
    wire is_u_instr = is_valid && ((opcode[6:2] == 5'b00101) || (opcode[6:2] == 5'b01101));
    wire is_j_instr = is_valid && (opcode[6:2] == 5'b11011);

    // ----------------------------------------------------
    // D) DECODIFICACIÓN DE INSTRUCCIONES DE SALTO
    // ----------------------------------------------------
    wire is_beq  = is_b_instr && (funct3 == 3'b000);
    wire is_bne  = is_b_instr && (funct3 == 3'b001);
    wire is_blt  = is_b_instr && (funct3 == 3'b100);
    wire is_bge  = is_b_instr && (funct3 == 3'b101);
    wire is_bltu = is_b_instr && (funct3 == 3'b110);
    wire is_bgeu = is_b_instr && (funct3 == 3'b111);

    // ----------------------------------------------------
    // EXTENSOR DE SIGNO (INMEDIATO)
    // ----------------------------------------------------
    wire [31:0] imm;
    wire imm_valid;

    assign imm = is_i_instr ? {{21{IR[31]}}, IR[30:20]} :
                 is_s_instr ? {{21{IR[31]}}, IR[30:25], IR[11:7]} :
                 is_b_instr ? {{20{IR[31]}}, IR[7], IR[30:25], IR[11:8], 1'b0} :
                 is_u_instr ? {IR[31], IR[30:20], IR[19:12], 12'b0} :
                 is_j_instr ? {{12{IR[31]}}, IR[19:12], IR[20], IR[30:25], IR[24:21], 1'b0} :
                 32'b0;

    assign imm_valid = is_i_instr || is_s_instr || is_b_instr || is_u_instr || is_j_instr;

    // ----------------------------------------------------
    // DECODIFICACIÓN DE OPERACIONES ALU
    // ----------------------------------------------------
    wire [10:0] dec_bits  = {funct7[5], funct3, opcode};
    wire [9:0]  dec_bits2 = {funct3, opcode};

    wire is_add  = (dec_bits  == 11'b0_000_0110011);
    wire is_sub  = (dec_bits  == 11'b1_000_0110011);
    wire is_and  = (dec_bits  == 11'b0_111_0110011);
    wire is_or   = (dec_bits  == 11'b0_110_0110011);
    wire is_xor  = (dec_bits  == 11'b0_100_0110011);

    wire is_addi = (dec_bits2 == 10'b000_0010011);
    wire is_andi = (dec_bits2 == 10'b111_0010011);
    wire is_ori  = (dec_bits2 == 10'b110_0010011);
    wire is_xori = (dec_bits2 == 10'b100_0010011);

    // Habilitación de Escritura (Solo activa en el estado EXECUTE)
    wire wr_en_dec = is_r_instr || is_i_instr || is_u_instr || is_j_instr;

    // ----------------------------------------------------
    // CONEXIÓN DEL REGISTER FILE Y LA ALU
    // ----------------------------------------------------
    wire [31:0] src1_value;
    wire [31:0] src2_value;
    wire [31:0] alu_a;
    wire [31:0] alu_b;
    wire [31:0] alu_out;

    // Escritura condicional sincronizada con EXECUTE
    registerfile rf (
        .clk(clk),
        .wr_en(wr_en_dec & state_execute),
        .wr_index(rd),
        .wr_data(alu_out),
        .rd_index1(rs1),
        .rd_data1(src1_value),
        .rd_index2(rs2),
        .rd_data2(src2_value)
    );

    assign alu_a = src1_value;
    assign alu_b = imm_valid ? imm : src2_value;

    alu rv_alu (
        .a(alu_a),
        .b(alu_b),
        .op(
            (is_add || is_addi) ? 3'b000 :
            (is_sub)            ? 3'b001 :
            (is_and || is_andi) ? 3'b010 :
            (is_or  || is_ori)  ? 3'b011 :
                                  3'b100
        ),
        .ALU_out(alu_out)
    );

    // ----------------------------------------------------
    // D) COMPARADOR Y LÓGICA DEL PROGRAM COUNTER (PC)
    // ----------------------------------------------------
    // Comparaciones entre rs1 y rs2
    wire eq  = (src1_value == src2_value);
    wire ne  = (src1_value != src2_value);
    wire lt  = ($signed(src1_value) < $signed(src2_value));
    wire ge  = ($signed(src1_value) >= $signed(src2_value));
    wire ltu = (src1_value < src2_value);
    wire geu = (src1_value >= src2_value);

    // Evaluación de la condición de salto
    wire taken_br = is_beq  ? eq  :
                    is_bne  ? ne  :
                    is_blt  ? lt  :
                    is_bge  ? ge  :
                    is_bltu ? ltu :
                    is_bgeu ? geu : 1'b0;

    // Cálculo de direcciones objetivo
    wire [31:0] pc_plus_4 = pc + 32'd4;
    wire [31:0] br_tgt_pc = pc + imm;
    wire [31:0] next_pc   = (taken_br || is_j_instr) ? br_tgt_pc : pc_plus_4;

    // Actualización del PC únicamente en la fase EXECUTE
    always @(posedge clk) begin
        if (rst)
            pc <= 32'd0;
        else if (state_execute)
            pc <= next_pc;
    end

endmodule

digitales2/digitales2/mcu_tb.v
`timescale 1ns/1ps

// Test bench para el microcontrolador
module mcu_tb;

    // Señales de prueba
    reg clk;
    reg rst;

    // Instancia del microcontrolador
    mcu mcuuq (
        .rst(rst),
        .clk(clk)
    );

    integer i;

    // Bloque inicial: aplica estímulos
    initial begin
        // Configurar la generación de archivos de volcado para GTKWave
        $dumpfile("tb_mcu.vcd");
        $dumpvars(0, mcu_tb);

        // Guarda el valor de los 32 registros del Register File para verlos en la onda
        for (i = 0; i < 32; i = i + 1) 
            $dumpvars(0, mcuuq.cpu.rf.RF[i]);

        #0; 
        clk = 0;
        rst = 1;

        #93; 
        rst = 0; // Libera el reset para empezar a ejecutar el programa

        #400; // Termina después de aproximadamente 60 ciclos de reloj

        #16;
        // Fin de la simulación
        $finish;
    end

    // Generación de la señal de reloj (Periodo = 4ns)
    always begin
        #2 clk = !clk;
    end

endmodule

digitales2/digitales2/tb_mcu.vcd
$date
	Thu Sep 24 22:34:51 2026
$end
$version
	Icarus Verilog
$end
$timescale
	1ps
$end
$scope module mcu_tb $end
$var reg 1 ! clk $end
$var reg 1 " rst $end
$var integer 32 # i [31:0] $end
$scope module mcuuq $end
$var wire 1 ! clk $end
$var wire 32 $ daddr [31:0] $end
$var wire 32 % ddata_in [31:0] $end
$var wire 32 & ddata_out [31:0] $end
$var wire 1 ' drd_en $end
$var wire 1 ( dwr_en $end
$var wire 1 " rst $end
$var wire 32 ) instr [31:0] $end
$var wire 32 * iaddr [31:0] $end
$scope module IMEM $end
$var wire 12 + addr [11:0] $end
$var reg 32 , data [31:0] $end
$upscope $end
$scope module cpu $end
$var wire 32 - alu_a [31:0] $end
$var wire 1 ! clk $end
$var wire 32 . daddr [31:0] $end
$var wire 32 / ddata_in [31:0] $end
$var wire 32 0 ddata_out [31:0] $end
$var wire 1 ' drd_en $end
$var wire 1 ( dwr_en $end
$var wire 32 1 iaddr [31:0] $end
$var wire 1 2 imm_valid $end
$var wire 32 3 instr [31:0] $end
$var wire 1 4 is_b_instr $end
$var wire 1 5 is_beq $end
$var wire 1 6 is_bge $end
$var wire 1 7 is_bgeu $end
$var wire 1 8 is_blt $end
$var wire 1 9 is_bltu $end
$var wire 1 : is_bne $end
$var wire 1 ; is_i_instr $end
$var wire 1 < is_j_instr $end
$var wire 1 = is_r_instr $end
$var wire 1 > is_s_instr $end
$var wire 1 ? is_u_instr $end
$var wire 1 " rst $end
$var wire 1 @ wr_en_dec $end
$var wire 1 A taken_br $end
$var wire 32 B src2_value [31:0] $end
$var wire 32 C src1_value [31:0] $end
$var wire 5 D rs2 [4:0] $end
$var wire 5 E rs1 [4:0] $end
$var wire 5 F rd [4:0] $end
$var wire 32 G pc_plus_4 [31:0] $end
$var wire 7 H opcode [6:0] $end
$var wire 32 I next_pc [31:0] $end
$var wire 1 J ne $end
$var wire 1 K ltu $end
$var wire 1 L lt $end
$var wire 1 M is_xori $end
$var wire 1 N is_xor $end
$var wire 1 O is_valid $end
$var wire 1 P is_sub $end
$var wire 1 Q is_ori $end
$var wire 1 R is_or $end
$var wire 1 S is_andi $end
$var wire 1 T is_and $end
$var wire 1 U is_addi $end
$var wire 1 V is_add $end
$var wire 32 W imm [31:0] $end
$var wire 1 X geu $end
$var wire 1 Y ge $end
$var wire 7 Z funct7 [6:0] $end
$var wire 3 [ funct3 [2:0] $end
$var wire 1 \ eq $end
$var wire 10 ] dec_bits2 [9:0] $end
$var wire 11 ^ dec_bits [10:0] $end
$var wire 32 _ br_tgt_pc [31:0] $end
$var wire 32 ` alu_out [31:0] $end
$var wire 32 a alu_b [31:0] $end
$var reg 32 b IR [31:0] $end
$var reg 32 c pc [31:0] $end
$var reg 1 d state_decode $end
$var reg 1 e state_execute $end
$var reg 1 f state_fetch $end
$scope module rf $end
$var wire 1 ! clk $end
$var wire 5 g rd_index1 [4:0] $end
$var wire 5 h rd_index2 [4:0] $end
$var wire 1 i wr_en $end
$var wire 5 j wr_index [4:0] $end
$var wire 32 k wr_data [31:0] $end
$var wire 32 l rd_data2 [31:0] $end
$var wire 32 m rd_data1 [31:0] $end
$var integer 32 n i [31:0] $end
$upscope $end
$scope module rv_alu $end
$var wire 32 o a [31:0] $end
$var wire 32 p b [31:0] $end
$var wire 3 q op [2:0] $end
$var wire 32 r ALU_out [31:0] $end
$upscope $end
$upscope $end
$upscope $end
$upscope $end
$scope module mcu_tb $end
$scope module mcuuq $end
$scope module cpu $end
$scope module rf $end
$var reg 32 s \RF[0] [31:0] $end
$upscope $end
$upscope $end
$upscope $end
$upscope $end
$scope module mcu_tb $end
$scope module mcuuq $end
$scope module cpu $end
$scope module rf $end
$var reg 32 t \RF[1] [31:0] $end
$upscope $end
$upscope $end
$upscope $end
$upscope $end
$scope module mcu_tb $end
$scope module mcuuq $end
$scope module cpu $end
$scope module rf $end
$var reg 32 u \RF[2] [31:0] $end
$upscope $end
$upscope $end
$upscope $end
$upscope $end
$scope module mcu_tb $end
$scope module mcuuq $end
$scope module cpu $end
$scope module rf $end
$var reg 32 v \RF[3] [31:0] $end
$upscope $end
$upscope $end
$upscope $end
$upscope $end
$scope module mcu_tb $end
$scope module mcuuq $end
$scope module cpu $end
$scope module rf $end
$var reg 32 w \RF[4] [31:0] $end
$upscope $end
$upscope $end
$upscope $end
$upscope $end
$scope module mcu_tb $end
$scope module mcuuq $end
$scope module cpu $end
$scope module rf $end
$var reg 32 x \RF[5] [31:0] $end
$upscope $end
$upscope $end
$upscope $end
$upscope $end
$scope module mcu_tb $end
$scope module mcuuq $end
$scope module cpu $end
$scope module rf $end
$var reg 32 y \RF[6] [31:0] $end
$upscope $end
$upscope $end
$upscope $end
$upscope $end
$scope module mcu_tb $end
$scope module mcuuq $end
$scope module cpu $end
$scope module rf $end
$var reg 32 z \RF[7] [31:0] $end
$upscope $end
$upscope $end
$upscope $end
$upscope $end
$scope module mcu_tb $end
$scope module mcuuq $end
$scope module cpu $end
$scope module rf $end
$var reg 32 { \RF[8] [31:0] $end
$upscope $end
$upscope $end
$upscope $end
$upscope $end
$scope module mcu_tb $end
$scope module mcuuq $end
$scope module cpu $end
$scope module rf $end
$var reg 32 | \RF[9] [31:0] $end
$upscope $end
$upscope $end
$upscope $end
$upscope $end
$scope module mcu_tb $end
$scope module mcuuq $end
$scope module cpu $end
$scope module rf $end
$var reg 32 } \RF[10] [31:0] $end
$upscope $end
$upscope $end
$upscope $end
$upscope $end
$scope module mcu_tb $end
$scope module mcuuq $end
$scope module cpu $end
$scope module rf $end
$var reg 32 ~ \RF[11] [31:0] $end
$upscope $end
$upscope $end
$upscope $end
$upscope $end
$scope module mcu_tb $end
$scope module mcuuq $end
$scope module cpu $end
$scope module rf $end
$var reg 32 !" \RF[12] [31:0] $end
$upscope $end
$upscope $end
$upscope $end
$upscope $end
$scope module mcu_tb $end
$scope module mcuuq $end
$scope module cpu $end
$scope module rf $end
$var reg 32 "" \RF[13] [31:0] $end
$upscope $end
$upscope $end
$upscope $end
$upscope $end
$scope module mcu_tb $end
$scope module mcuuq $end
$scope module cpu $end
$scope module rf $end
$var reg 32 #" \RF[14] [31:0] $end
$upscope $end
$upscope $end
$upscope $end
$upscope $end
$scope module mcu_tb $end
$scope module mcuuq $end
$scope module cpu $end
$scope module rf $end
$var reg 32 $" \RF[15] [31:0] $end
$upscope $end
$upscope $end
$upscope $end
$upscope $end
$scope module mcu_tb $end
$scope module mcuuq $end
$scope module cpu $end
$scope module rf $end
$var reg 32 %" \RF[16] [31:0] $end
$upscope $end
$upscope $end
$upscope $end
$upscope $end
$scope module mcu_tb $end
$scope module mcuuq $end
$scope module cpu $end
$scope module rf $end
$var reg 32 &" \RF[17] [31:0] $end
$upscope $end
$upscope $end
$upscope $end
$upscope $end
$scope module mcu_tb $end
$scope module mcuuq $end
$scope module cpu $end
$scope module rf $end
$var reg 32 '" \RF[18] [31:0] $end
$upscope $end
$upscope $end
$upscope $end
$upscope $end
$scope module mcu_tb $end
$scope module mcuuq $end
$scope module cpu $end
$scope module rf $end
$var reg 32 (" \RF[19] [31:0] $end
$upscope $end
$upscope $end
$upscope $end
$upscope $end
$scope module mcu_tb $end
$scope module mcuuq $end
$scope module cpu $end
$scope module rf $end
$var reg 32 )" \RF[20] [31:0] $end
$upscope $end
$upscope $end
$upscope $end
$upscope $end
$scope module mcu_tb $end
$scope module mcuuq $end
$scope module cpu $end
$scope module rf $end
$var reg 32 *" \RF[21] [31:0] $end
$upscope $end
$upscope $end
$upscope $end
$upscope $end
$scope module mcu_tb $end
$scope module mcuuq $end
$scope module cpu $end
$scope module rf $end
$var reg 32 +" \RF[22] [31:0] $end
$upscope $end
$upscope $end
$upscope $end
$upscope $end
$scope module mcu_tb $end
$scope module mcuuq $end
$scope module cpu $end
$scope module rf $end
$var reg 32 ," \RF[23] [31:0] $end
$upscope $end
$upscope $end
$upscope $end
$upscope $end
$scope module mcu_tb $end
$scope module mcuuq $end
$scope module cpu $end
$scope module rf $end
$var reg 32 -" \RF[24] [31:0] $end
$upscope $end
$upscope $end
$upscope $end
$upscope $end
$scope module mcu_tb $end
$scope module mcuuq $end
$scope module cpu $end
$scope module rf $end
$var reg 32 ." \RF[25] [31:0] $end
$upscope $end
$upscope $end
$upscope $end
$upscope $end
$scope module mcu_tb $end
$scope module mcuuq $end
$scope module cpu $end
$scope module rf $end
$var reg 32 /" \RF[26] [31:0] $end
$upscope $end
$upscope $end
$upscope $end
$upscope $end
$scope module mcu_tb $end
$scope module mcuuq $end
$scope module cpu $end
$scope module rf $end
$var reg 32 0" \RF[27] [31:0] $end
$upscope $end
$upscope $end
$upscope $end
$upscope $end
$scope module mcu_tb $end
$scope module mcuuq $end
$scope module cpu $end
$scope module rf $end
$var reg 32 1" \RF[28] [31:0] $end
$upscope $end
$upscope $end
$upscope $end
$upscope $end
$scope module mcu_tb $end
$scope module mcuuq $end
$scope module cpu $end
$scope module rf $end
$var reg 32 2" \RF[29] [31:0] $end
$upscope $end
$upscope $end
$upscope $end
$upscope $end
$scope module mcu_tb $end
$scope module mcuuq $end
$scope module cpu $end
$scope module rf $end
$var reg 32 3" \RF[30] [31:0] $end
$upscope $end
$upscope $end
$upscope $end
$upscope $end
$scope module mcu_tb $end
$scope module mcuuq $end
$scope module cpu $end
$scope module rf $end
$var reg 32 4" \RF[31] [31:0] $end
$upscope $end
$upscope $end
$upscope $end
$upscope $end
$enddefinitions $end
$comment Show the parameter values. $end
$dumpall
$end
#0
$dumpvars
b0 4"
b0 3"
b0 2"
b0 1"
b0 0"
b0 /"
b0 ."
b0 -"
b0 ,"
b0 +"
b0 *"
b0 )"
b0 ("
b0 '"
b0 &"
b0 %"
b0 $"
b0 #"
b0 ""
b0 !"
b0 ~
b0 }
b0 |
b0 {
b0 z
b0 y
b0 x
b0 w
b0 v
b0 u
b0 t
b0 s
bx r
bx q
bx p
bx o
b100000 n
bx m
bx l
bx k
bx j
0i
bx h
bx g
1f
0e
0d
bx c
bx b
bx a
bx `
bx _
bx ^
bx ]
x\
bx [
bx Z
xY
xX
bx W
xV
xU
xT
xS
xR
xQ
xP
xO
xN
xM
xL
xK
xJ
bx I
bx H
bx G
bx F
bx E
bx D
bx C
bx B
xA
x@
x?
x>
x=
x<
x;
x:
x9
x8
x7
x6
x5
x4
bx 3
x2
bx 1
b0 0
bz /
b0 .
bx -
bx ,
bx +
bx *
bx )
0(
0'
b0 &
bz %
b0 $
b100000 #
1"
0!
$end
#2000
b0 _
02
b100 I
b0 `
b0 k
b0 r
b100 q
0@
0A
05
b0 a
b0 p
0?
0>
0=
0;
04
0<
b0 W
1X
0K
1Y
0L
0J
1\
b0 B
b0 l
b0 -
b0 o
b0 C
b0 m
0:
08
06
09
07
0O
0V
0P
0T
0R
0N
b0 ^
0U
0S
0Q
0M
b0 ]
b110110011 )
b110110011 ,
b110110011 3
b0 Z
b0 D
b0 h
b0 E
b0 g
b0 [
b0 F
b0 j
b0 H
b0 +
b0 s
b0 b
b100 G
b0 *
b0 1
b0 c
1!
#4000
0!
#6000
b0 s
1!
#8000
0!
#10000
02
1@
1=
b0 q
0;
1O
1V
b110011 ^
b110011 ]
b11 F
b11 j
b110011 H
b0 s
b110110011 b
1!
0"
#12000
1d
0f
0!
#14000
b0 s
1!
#16000
1i
1e
0d
0!
#18000
b1010110011 )
b1010110011 ,
b1010110011 3
b1000 I
b1 +
b0 s
b0 v
b1000 G
b100 _
b100 *
b100 1
b100 c
1!
#20000
0i
0e
1f
0!
#22000
b101 F
b101 j
b1010110011 b
b0 s
1!
#24000
1d
0f
0!
#26000
b0 s
1!
#28000
1i
1e
0d
0!
#30000
b10100000000001100010011 )
b10100000000001100010011 ,
b10100000000001100010011 3
b1100 I
b10 +
b1100 G
b1000 _
b1000 *
b1000 1
b1000 c
b0 s
b0 x
1!
#32000
0i
0e
1f
0!
#34000
b101 `
b101 k
b101 r
b101 a
b101 p
12
b1101 _
b101 W
1;
0=
0V
b10011 ^
1U
b10011 ]
b101 D
b101 h
b110 F
b110 j
b10011 H
b0 s
b10100000000001100010011 b
1!
#36000
1d
0f
0!
#38000
b0 s
1!
#40000
1i
1e
0d
0!
#42000
b10100101000000110110011 )
b10100101000000110110011 ,
b10100101000000110110011 3
b10000 I
b11 +
b0 s
b101 y
b10000 G
b10001 _
b1100 *
b1100 1
b1100 c
1!
#44000
0i
0e
1f
0!
#46000
02
b0 `
b0 k
b0 r
b0 a
b0 p
b1100 _
b0 W
0;
1=
1V
b110011 ^
0U
b110011 ]
b101 E
b101 g
b11 F
b11 j
b110011 H
b10100101000000110110011 b
b0 s
1!
#48000
1d
0f
0!
#50000
b0 s
1!
#52000
1i
1e
0d
0!
#54000
b100101000001010010011 )
b100101000001010010011 ,
b100101000001010010011 3
b10100 I
b100 +
b10100 G
b10000 _
b10000 *
b10000 1
b10000 c
b0 s
b0 v
1!
#56000
0i
0e
1f
0!
#58000
b1 `
b1 k
b1 r
b1 a
b1 p
12
b10001 _
b1 W
1;
0=
0V
b10011 ^
1U
b10011 ]
b1 D
b1 h
b101 F
b101 j
b10011 H
b0 s
b100101000001010010011 b
1!
#60000
1d
0f
0!
#62000
b0 s
1!
#64000
1i
1e
0d
0!
#66000
b10 `
b10 k
b10 r
b11111110011000101100110011100011 )
b11111110011000101100110011100011 ,
b11111110011000101100110011100011 3
1J
0\
b1 -
b1 o
b1 C
b1 m
b11000 I
b101 +
b0 s
b1 x
b11000 G
b10101 _
b10100 *
b10100 1
b10100 c
1!
#68000
0i
0e
1f
0!
#70000
b1100 I
0@
1A
0;
b11111111111111111111111111111001 `
b11111111111111111111111111111001 k
b11111111111111111111111111111001 r
18
b100 q
b11111111111111111111111111111000 a
b11111111111111111111111111111000 p
0X
1K
0Y
1L
b101 B
b101 l
14
b1100 _
b11111111111111111111111111111000 W
b11001100011 ^
0U
b1001100011 ]
b1111111 Z
b110 D
b110 h
b100 [
b11001 F
b11001 j
b1100011 H
b11111110011000101100110011100011 b
b0 s
1!
#72000
1d
0f
0!
#74000
b0 s
1!
#76000
1e
0d
0!
#78000
b10100101000000110110011 )
b10100101000000110110011 ,
b10100101000000110110011 3
b100 I
b11 +
b10000 G
b100 _
b1100 *
b1100 1
b1100 c
b0 s
1!
#80000
0e
1f
0!
#82000
1@
b10 `
b10 k
b10 r
b1 a
b1 p
02
b1100 _
b0 W
b10000 I
1=
b0 q
1V
1X
0K
1Y
0L
0J
1\
b1 B
b1 l
0A
04
05
08
0P
b110011 ^
b110011 ]
b0 Z
b101 D
b101 h
b0 [
b11 F
b11 j
b110011 H
b0 s
b10100101000000110110011 b
1!
#84000
1d
0f
0!
#86000
b0 s
1!
#88000
1i
1e
0d
0!
#90000
b100101000001010010011 )
b100101000001010010011 ,
b100101000001010010011 3
b10100 I
b100 +
b0 s
b10 v
b10100 G
b10000 _
b10000 *
b10000 1
b10000 c
1!
#92000
0i
0e
1f
0!
#94000
12
b10001 _
b1 W
b10 `
b10 k
b10 r
1;
0=
b1 a
b1 p
1J
0\
b0 B
b0 l
0V
b10011 ^
1U
b10011 ]
b1 D
b1 h
b101 F
b101 j
b10011 H
b100101000001010010011 b
b0 s
1!
#96000
1d
0f
0!
#98000
b0 s
1!
#100000
1i
1e
0d
0!
#102000
b11111110011000101100110011100011 )
b11111110011000101100110011100011 ,
b11111110011000101100110011100011 3
b11 `
b11 k
b11 r
b11000 I
b101 +
b10 -
b10 o
b10 C
b10 m
b11000 G
b10101 _
b10100 *
b10100 1
b10100 c
b0 s
b10 x
1!
#104000
0i
0e
1f
0!
#106000
b1100 I
0@
1A
0;
b11111111111111111111111111111010 `
b11111111111111111111111111111010 k
b11111111111111111111111111111010 r
18
b100 q
b11111111111111111111111111111000 a
b11111111111111111111111111111000 p
0X
1K
0Y
1L
b101 B
b101 l
14
b1100 _
b11111111111111111111111111111000 W
b11001100011 ^
0U
b1001100011 ]
b1111111 Z
b110 D
b110 h
b100 [
b11001 F
b11001 j
b1100011 H
b0 s
b11111110011000101100110011100011 b
1!
#108000
1d
0f
0!
#110000
b0 s
1!
#112000
1e
0d
0!
#114000
b10100101000000110110011 )
b10100101000000110110011 ,
b10100101000000110110011 3
b100 I
b11 +
b0 s
b10000 G
b100 _
b1100 *
b1100 1
b1100 c
1!
#116000
0e
1f
0!
#118000
1@
b100 `
b100 k
b100 r
b10 a
b10 p
02
b1100 _
b0 W
b10000 I
1=
b0 q
1V
1X
0K
1Y
0L
0J
1\
b10 B
b10 l
0A
04
05
08
0P
b110011 ^
b110011 ]
b0 Z
b101 D
b101 h
b0 [
b11 F
b11 j
b110011 H
b10100101000000110110011 b
b0 s
1!
#120000
1d
0f
0!
#122000
b0 s
1!
#124000
1i
1e
0d
0!
#126000
b100101000001010010011 )
b100101000001010010011 ,
b100101000001010010011 3
b10100 I
b100 +
b10100 G
b10000 _
b10000 *
b10000 1
b10000 c
b0 s
b100 v
1!
#128000
0i
0e
1f
0!
#130000
12
b10001 _
b1 W
b11 `
b11 k
b11 r
1;
0=
b1 a
b1 p
1J
0\
b0 B
b0 l
0V
b10011 ^
1U
b10011 ]
b1 D
b1 h
b101 F
b101 j
b10011 H
b0 s
b100101000001010010011 b
1!
#132000
1d
0f
0!
#134000
b0 s
1!
#136000
1i
1e
0d
0!
#138000
b100 `
b100 k
b100 r
b11111110011000101100110011100011 )
b11111110011000101100110011100011 ,
b11111110011000101100110011100011 3
b11 -
b11 o
b11 C
b11 m
b11000 I
b101 +
b0 s
b11 x
b11000 G
b10101 _
b10100 *
b10100 1
b10100 c
1!
#140000
0i
0e
1f
0!
#142000
b1100 I
0@
1A
0;
b11111111111111111111111111111011 `
b11111111111111111111111111111011 k
b11111111111111111111111111111011 r
18
b100 q
b11111111111111111111111111111000 a
b11111111111111111111111111111000 p
0X
1K
0Y
1L
b101 B
b101 l
14
b1100 _
b11111111111111111111111111111000 W
b11001100011 ^
0U
b1001100011 ]
b1111111 Z
b110 D
b110 h
b100 [
b11001 F
b11001 j
b1100011 H
b11111110011000101100110011100011 b
b0 s
1!
#144000
1d
0f
0!
#146000
b0 s
1!
#148000
1e
0d
0!
#150000
b10100101000000110110011 )
b10100101000000110110011 ,
b10100101000000110110011 3
b100 I
b11 +
b10000 G
b100 _
b1100 *
b1100 1
b1100 c
b0 s
1!
#152000
0e
1f
0!
#154000
1@
b110 `
b110 k
b110 r
b11 a
b11 p
02
b1100 _
b0 W
b10000 I
1=
b0 q
1V
1X
0K
1Y
0L
0J
1\
b11 B
b11 l
0A
04
05
08
0P
b110011 ^
b110011 ]
b0 Z
b101 D
b101 h
b0 [
b11 F
b11 j
b110011 H
b0 s
b10100101000000110110011 b
1!
#156000
1d
0f
0!
#158000
b0 s
1!
#160000
1i
1e
0d
0!
#162000
b100101000001010010011 )
b100101000001010010011 ,
b100101000001010010011 3
b10100 I
b100 +
b0 s
b110 v
b10100 G
b10000 _
b10000 *
b10000 1
b10000 c
1!
#164000
0i
0e
1f
0!
#166000
12
b10001 _
b1 W
b100 `
b100 k
b100 r
1;
0=
b1 a
b1 p
1J
0\
b0 B
b0 l
0V
b10011 ^
1U
b10011 ]
b1 D
b1 h
b101 F
b101 j
b10011 H
b100101000001010010011 b
b0 s
1!
#168000
1d
0f
0!
#170000
b0 s
1!
#172000
1i
1e
0d
0!
