digitales2/alu.v
module alu (
    input wire [31:0] a,
    input wire [31:0] b,
    input wire [2:0] op,
    output wire [31:0] ALU_out
);

assign ALU_out =
    (op == 3'b000) ? a + b :
    (op == 3'b001) ? a - b :
    (op == 3'b010) ? a & b :
    (op == 3'b011) ? a | b :
                     a ^ b;

endmodule

digitales2/digitales2/registerfile.v
module registerfile(
    input  wire        clk,
    input  wire        wr_en,
    input  wire [4:0]  wr_index,
    input  wire [31:0] wr_data,

    input  wire [4:0]  rd_index1,
    input  wire [4:0]  rd_index2,

    output wire [31:0] rd_data1,
    output wire [31:0] rd_data2
);

    // Banco de 32 registros de 32 bits
    reg [31:0] RF [0:31];

    integer i;

    // Inicialización para simulación
    initial begin
        for (i = 0; i < 32; i = i + 1)
            RF[i] = 32'd0;
    end

    // Escritura síncrona
    always @(posedge clk) begin
        if (wr_en && (wr_index != 5'd0))
            RF[wr_index] <= wr_data;

        // x0 siempre permanece en cero
        RF[0] <= 32'd0;
    end

    // Lectura combinacional
    assign rd_data1 = (rd_index1 == 5'd0) ? 32'd0 : RF[rd_index1];
    assign rd_data2 = (rd_index2 == 5'd0) ? 32'd0 : RF[rd_index2];

endmodule

digitales2/riscv.v
module riscv (
    input wire clk,
    input wire rst,
    input wire [31:0] instr
);

    // ------------------------------------------------
    // REGISTRO DE INSTRUCCIÓN (IR)
    // ------------------------------------------------
    reg [31:0] IR;

    always @(posedge clk) begin
        if (rst)
            IR <= 32'b0;
        else
            IR <= instr;
    end

    // ------------------------------------------------
    // DECODIFICACIÓN DE CAMPOS
    // ------------------------------------------------
    wire [6:0] funct7;
    wire [4:0] rs2;
    wire [4:0] rs1;
    wire [2:0] funct3;
    wire [4:0] rd;
    wire [6:0] opcode;

    assign funct7 = IR[31:25];
    assign rs2    = IR[24:20];
    assign rs1    = IR[19:15];
    assign funct3 = IR[14:12];
    assign rd     = IR[11:7];
    assign opcode = IR[6:0];

    // ------------------------------------------------
    // TIPOS DE INSTRUCCIÓN SEGÚN OPCODE[6:2] 
    // ------------------------------------------------
    wire is_r_instr;
    wire is_i_instr;
    wire is_s_instr;
    wire is_b_instr;
    wire is_u_instr;
    wire is_j_instr;
    wire is_valid;

    // Validación de bits [1:0] (Deben ser 2'b11 según la guía)
    assign is_valid = (opcode[1:0] == 2'b11);

    // Detección por opcode[6:2]
    assign is_i_instr = is_valid && (
                            (opcode[6:2] == 5'b00000) || // Load
                            (opcode[6:2] == 5'b00001) || // Fence
                            (opcode[6:2] == 5'b00100) || // OP-IMM (addi, andi, etc.)
                            (opcode[6:2] == 5'b11001)    // JALR
                        );

    assign is_r_instr = is_valid && (
                            (opcode[6:2] == 5'b01100) || // OP (add, sub, etc.)
                            (opcode[6:2] == 5'b01101) || 
                            (opcode[6:2] == 5'b10100)
                        );

    assign is_s_instr = is_valid && ((opcode[6:2] == 5'b01000) || (opcode[6:2] == 5'b01001));
    assign is_b_instr = is_valid && (opcode[6:2] == 5'b11000);
    assign is_u_instr = is_valid && ((opcode[6:2] == 5'b00101) || (opcode[6:2] == 5'b01101));
    assign is_j_instr = is_valid && (opcode[6:2] == 5'b11011);

    // ------------------------------------------------
    // EXTENSOR DE SIGNO (INMEDIATO)
    // ------------------------------------------------
    wire [31:0] imm;
    wire imm_valid;

    assign imm = is_i_instr ? {{21{IR[31]}}, IR[30:20]} :
                 is_s_instr ? {{21{IR[31]}}, IR[30:25], IR[11:7]} :
                 is_b_instr ? {{20{IR[31]}}, IR[7], IR[30:25], IR[11:8], 1'b0} :
                 is_u_instr ? {IR[31], IR[30:20], IR[19:12], 12'b0} :
                 is_j_instr ? {{12{IR[31]}}, IR[19:12], IR[20], IR[30:25], IR[24:21], 1'b0} :
                 32'b0;

    assign imm_valid = is_i_instr || is_s_instr || is_b_instr || is_u_instr || is_j_instr;

    // ------------------------------------------------
    // DECODIFICACIÓN DE OPERACIONES ALU
    // ------------------------------------------------
    wire [10:0] dec_bits;
    wire [9:0]  dec_bits2;

    wire is_add, is_sub, is_and, is_or, is_xor;
    wire is_addi, is_andi, is_ori, is_xori;

    assign dec_bits  = {funct7[5], funct3, opcode};
    assign dec_bits2 = {funct3, opcode};

    // Instrucciones R
    assign is_add = (dec_bits == 11'b0_000_0110011);
    assign is_sub = (dec_bits == 11'b1_000_0110011);
    assign is_and = (dec_bits == 11'b0_111_0110011);
    assign is_or  = (dec_bits == 11'b0_110_0110011);
    assign is_xor = (dec_bits == 11'b0_100_0110011);

    // Instrucciones I
    assign is_addi = (dec_bits2 == 10'b000_0010011);
    assign is_andi = (dec_bits2 == 10'b111_0010011);
    assign is_ori  = (dec_bits2 == 10'b110_0010011);
    assign is_xori = (dec_bits2 == 10'b100_0010011);

    // Habilitación de Escritura (wr_en)
    wire wr_en;
    assign wr_en = is_r_instr || is_i_instr || is_u_instr || is_j_instr;

    // ------------------------------------------------
    // CONEXIÓN DEL REGISTER FILE Y LA ALU
    // ------------------------------------------------
    wire [31:0] src1_value;
    wire [31:0] src2_value;
    wire [31:0] alu_a;
    wire [31:0] alu_b;
    wire [31:0] alu_out;

    registerfile rf (
        .clk(clk),
        .wr_en(wr_en),
        .wr_index(rd),
        .wr_data(alu_out),
        .rd_index1(rs1),
        .rd_data1(src1_value),
        .rd_index2(rs2),
        .rd_data2(src2_value)
    );

    // Selección de la entrada B de la ALU
    assign alu_a = src1_value;
    assign alu_b = imm_valid ? imm : src2_value;

    alu rv_alu (
        .a(alu_a),
        .b(alu_b),
        .op(
            (is_add || is_addi) ? 3'b000 :
            (is_sub)            ? 3'b001 :
            (is_and || is_andi) ? 3'b010 :
            (is_or  || is_ori)  ? 3'b011 :
                                  3'b100  // XOR / XORI
        ),
        .ALU_out(alu_out)
    );

endmodule

digitales2/riscv_tb.v
`timescale 1ns/1ps

module tb_riscv;

    // Señales de prueba
    reg [31:0] instr;
    reg clk;
    reg rst;

    // Instancia del procesador
    riscv uut (
        .clk(clk),
        .rst(rst),
        .instr(instr)
    );

    integer i;

    initial begin

        // Archivo de simulación
        $dumpfile("tb_riscv.vcd");
        $dumpvars(0, tb_riscv);

        // Guardar todos los registros
        for (i = 0; i < 32; i = i + 1)
            $dumpvars(0, uut.rf.RF[i]);

        // Inicializar los registros: xN = N
        for (i = 0; i < 32; i = i + 1)
            uut.rf.RF[i] = i;

        // Mostrar registros importantes en tiempo de simulación
        $monitor($time,
                 " clk=%d | rst=%d | instr=%h | x4=%h | x5=%h | x6=%h | x7=%h | x8=%h",
                 clk,
                 rst,
                 instr,
                 uut.rf.RF[4],
                 uut.rf.RF[5],
                 uut.rf.RF[6],
                 uut.rf.RF[7],
                 uut.rf.RF[8]);

        // Estado inicial
        #0;
        clk = 0;
        rst = 1;
        instr = 32'b0;

        // Liberar reset
        #3;
        rst = 0;


        // ------------------------------------------------
        // PRUEBA 1: ADDI
        // x4 = x3 + 10
        // Esperado: x4 = 3 + 10 = 13 (0x0000000D)
        // ------------------------------------------------
        instr = 32'h00a18213; // ADDI x4, x3, 10
        $display("========================================");
        $display("PRUEBA 1: ADDI x4, x3, 10");
        $display("Esperado: x4 = 13 (0x0000000D)");

        #12;


        // ------------------------------------------------
        // PRUEBA 2: ANDI
        // x6 = x10 & 12
        // Esperado: x6 = 10 & 12 = 8 (0x00000008)
        // ------------------------------------------------
        instr = 32'h00c57313; // ANDI x6, x10, 12
        $display("========================================");
        $display("PRUEBA 2: ANDI x6, x10, 12");
        $display("Esperado: x6 = 8 (0x00000008)");

        #12;


        // ------------------------------------------------
        // PRUEBA 3: ORI
        // x8 = x10 | 12
        // Esperado: x8 = 10 | 12 = 14 (0x0000000E)
        // ------------------------------------------------
        instr = 32'h00c56413; // ORI x8, x10, 12
        $display("========================================");
        $display("PRUEBA 3: ORI x8, x10, 12");
        $display("Esperado: x8 = 14 (0x0000000E)");

        #12;


        // ------------------------------------------------
        // PRUEBA 4: XORI
        // x7 = x10 ^ 12
        // Esperado: x7 = 10 ^ 12 = 6 (0x00000006)
        // ------------------------------------------------
        instr = 32'h00c54393; // XORI x7, x10, 12
        $display("========================================");
        $display("PRUEBA 4: XORI x7, x10, 12");
        $display("Esperado: x7 = 6 (0x00000006)");

        #16;


        // Resumen final
        $display("========================================");
        $display("SIMULACION FINALIZADA");
        $display("x4 = %d (Esperado: 13)", uut.rf.RF[4]);
        $display("x6 = %d (Esperado: 8)",  uut.rf.RF[6]);
        $display("x7 = %d (Esperado: 6)",  uut.rf.RF[7]);
        $display("x8 = %d (Esperado: 14)", uut.rf.RF[8]);
        $display("========================================");

        $finish;

    end

    // Generador de reloj
    always begin
        #2 clk = ~clk;
    end

endmodule

digitales2/digitales2/tb_riscv.vcd
$date
	Mon Sep 21 21:25:20 2026
$end
$version
	Icarus Verilog
$end
$timescale
	1ps
$end
$scope module tb_riscv $end
$var reg 1 ! clk $end
$var reg 32 " instr [31:0] $end
$var reg 1 # rst $end
$var integer 32 $ i [31:0] $end
$scope module uut $end
$var wire 32 % alu_a [31:0] $end
$var wire 1 ! clk $end
$var wire 1 & imm_valid $end
$var wire 32 ' instr [31:0] $end
$var wire 1 ( is_b_instr $end
$var wire 1 ) is_i_instr $end
$var wire 1 * is_j_instr $end
$var wire 1 + is_r_instr $end
$var wire 1 , is_s_instr $end
$var wire 1 - is_u_instr $end
$var wire 1 # rst $end
$var wire 1 . wr_en $end
$var wire 32 / src2_value [31:0] $end
$var wire 32 0 src1_value [31:0] $end
$var wire 5 1 rs2 [4:0] $end
$var wire 5 2 rs1 [4:0] $end
$var wire 5 3 rd [4:0] $end
$var wire 7 4 opcode [6:0] $end
$var wire 1 5 is_xori $end
$var wire 1 6 is_xor $end
$var wire 1 7 is_valid $end
$var wire 1 8 is_sub $end
$var wire 1 9 is_ori $end
$var wire 1 : is_or $end
$var wire 1 ; is_andi $end
$var wire 1 < is_and $end
$var wire 1 = is_addi $end
$var wire 1 > is_add $end
$var wire 32 ? imm [31:0] $end
$var wire 7 @ funct7 [6:0] $end
$var wire 3 A funct3 [2:0] $end
$var wire 10 B dec_bits2 [9:0] $end
$var wire 11 C dec_bits [10:0] $end
$var wire 32 D alu_out [31:0] $end
$var wire 32 E alu_b [31:0] $end
$var reg 32 F IR [31:0] $end
$scope module rf $end
$var wire 1 ! clk $end
$var wire 5 G rd_index1 [4:0] $end
$var wire 5 H rd_index2 [4:0] $end
$var wire 1 . wr_en $end
$var wire 5 I wr_index [4:0] $end
$var wire 32 J wr_data [31:0] $end
$var wire 32 K rd_data2 [31:0] $end
$var wire 32 L rd_data1 [31:0] $end
$var integer 32 M i [31:0] $end
$upscope $end
$scope module rv_alu $end
$var wire 32 N a [31:0] $end
$var wire 32 O b [31:0] $end
$var wire 3 P op [2:0] $end
$var wire 32 Q ALU_out [31:0] $end
$upscope $end
$upscope $end
$upscope $end
$scope module tb_riscv $end
$scope module uut $end
$scope module rf $end
$var reg 32 R \RF[0] [31:0] $end
$upscope $end
$upscope $end
$upscope $end
$scope module tb_riscv $end
$scope module uut $end
$scope module rf $end
$var reg 32 S \RF[1] [31:0] $end
$upscope $end
$upscope $end
$upscope $end
$scope module tb_riscv $end
$scope module uut $end
$scope module rf $end
$var reg 32 T \RF[2] [31:0] $end
$upscope $end
$upscope $end
$upscope $end
$scope module tb_riscv $end
$scope module uut $end
$scope module rf $end
$var reg 32 U \RF[3] [31:0] $end
$upscope $end
$upscope $end
$upscope $end
$scope module tb_riscv $end
$scope module uut $end
$scope module rf $end
$var reg 32 V \RF[4] [31:0] $end
$upscope $end
$upscope $end
$upscope $end
$scope module tb_riscv $end
$scope module uut $end
$scope module rf $end
$var reg 32 W \RF[5] [31:0] $end
$upscope $end
$upscope $end
$upscope $end
$scope module tb_riscv $end
$scope module uut $end
$scope module rf $end
$var reg 32 X \RF[6] [31:0] $end
$upscope $end
$upscope $end
$upscope $end
$scope module tb_riscv $end
$scope module uut $end
$scope module rf $end
$var reg 32 Y \RF[7] [31:0] $end
$upscope $end
$upscope $end
$upscope $end
$scope module tb_riscv $end
$scope module uut $end
$scope module rf $end
$var reg 32 Z \RF[8] [31:0] $end
$upscope $end
$upscope $end
$upscope $end
$scope module tb_riscv $end
$scope module uut $end
$scope module rf $end
$var reg 32 [ \RF[9] [31:0] $end
$upscope $end
$upscope $end
$upscope $end
$scope module tb_riscv $end
$scope module uut $end
$scope module rf $end
$var reg 32 \ \RF[10] [31:0] $end
$upscope $end
$upscope $end
$upscope $end
$scope module tb_riscv $end
$scope module uut $end
$scope module rf $end
$var reg 32 ] \RF[11] [31:0] $end
$upscope $end
$upscope $end
$upscope $end
$scope module tb_riscv $end
$scope module uut $end
$scope module rf $end
$var reg 32 ^ \RF[12] [31:0] $end
$upscope $end
$upscope $end
$upscope $end
$scope module tb_riscv $end
$scope module uut $end
$scope module rf $end
$var reg 32 _ \RF[13] [31:0] $end
$upscope $end
$upscope $end
$upscope $end
$scope module tb_riscv $end
$scope module uut $end
$scope module rf $end
$var reg 32 ` \RF[14] [31:0] $end
$upscope $end
$upscope $end
$upscope $end
$scope module tb_riscv $end
$scope module uut $end
$scope module rf $end
$var reg 32 a \RF[15] [31:0] $end
$upscope $end
$upscope $end
$upscope $end
$scope module tb_riscv $end
$scope module uut $end
$scope module rf $end
$var reg 32 b \RF[16] [31:0] $end
$upscope $end
$upscope $end
$upscope $end
$scope module tb_riscv $end
$scope module uut $end
$scope module rf $end
$var reg 32 c \RF[17] [31:0] $end
$upscope $end
$upscope $end
$upscope $end
$scope module tb_riscv $end
$scope module uut $end
$scope module rf $end
$var reg 32 d \RF[18] [31:0] $end
$upscope $end
$upscope $end
$upscope $end
$scope module tb_riscv $end
$scope module uut $end
$scope module rf $end
$var reg 32 e \RF[19] [31:0] $end
$upscope $end
$upscope $end
$upscope $end
$scope module tb_riscv $end
$scope module uut $end
$scope module rf $end
$var reg 32 f \RF[20] [31:0] $end
$upscope $end
$upscope $end
$upscope $end
$scope module tb_riscv $end
$scope module uut $end
$scope module rf $end
$var reg 32 g \RF[21] [31:0] $end
$upscope $end
$upscope $end
$upscope $end
$scope module tb_riscv $end
$scope module uut $end
$scope module rf $end
$var reg 32 h \RF[22] [31:0] $end
$upscope $end
$upscope $end
$upscope $end
$scope module tb_riscv $end
$scope module uut $end
$scope module rf $end
$var reg 32 i \RF[23] [31:0] $end
$upscope $end
$upscope $end
$upscope $end
$scope module tb_riscv $end
$scope module uut $end
$scope module rf $end
$var reg 32 j \RF[24] [31:0] $end
$upscope $end
$upscope $end
$upscope $end
$scope module tb_riscv $end
$scope module uut $end
$scope module rf $end
$var reg 32 k \RF[25] [31:0] $end
$upscope $end
$upscope $end
$upscope $end
$scope module tb_riscv $end
$scope module uut $end
$scope module rf $end
$var reg 32 l \RF[26] [31:0] $end
$upscope $end
$upscope $end
$upscope $end
$scope module tb_riscv $end
$scope module uut $end
$scope module rf $end
$var reg 32 m \RF[27] [31:0] $end
$upscope $end
$upscope $end
$upscope $end
$scope module tb_riscv $end
$scope module uut $end
$scope module rf $end
$var reg 32 n \RF[28] [31:0] $end
$upscope $end
$upscope $end
$upscope $end
$scope module tb_riscv $end
$scope module uut $end
$scope module rf $end
$var reg 32 o \RF[29] [31:0] $end
$upscope $end
$upscope $end
$upscope $end
$scope module tb_riscv $end
$scope module uut $end
$scope module rf $end
$var reg 32 p \RF[30] [31:0] $end
$upscope $end
$upscope $end
$upscope $end
$scope module tb_riscv $end
$scope module uut $end
$scope module rf $end
$var reg 32 q \RF[31] [31:0] $end
$upscope $end
$upscope $end
$upscope $end
$enddefinitions $end
$comment Show the parameter values. $end
$dumpall
$end
#0
$dumpvars
b11111 q
b11110 p
b11101 o
b11100 n
b11011 m
b11010 l
b11001 k
b11000 j
b10111 i
b10110 h
b10101 g
b10100 f
b10011 e
b10010 d
b10001 c
b10000 b
b1111 a
b1110 `
b1101 _
b1100 ^
b1011 ]
b1010 \
b1001 [
b1000 Z
b111 Y
b110 X
b101 W
b100 V
b11 U
b10 T
b1 S
b0 R
bx Q
bx P
bx O
bx N
b100000 M
bx L
bx K
bx J
bx I
bx H
bx G
bx F
bx E
bx D
bx C
bx B
bx A
bx @
bx ?
x>
x=
x<
x;
x:
x9
x8
x7
x6
x5
bx 4
bx 3
bx 2
bx 1
bx 0
bx /
x.
x-
x,
x+
x*
x)
x(
b0 '
x&
bx %
b100000 $
1#
b0 "
0!
$end
#2000
0&
b0 D
b0 J
b0 Q
b100 P
0.
b0 E
b0 O
0-
0,
0+
0)
0(
0*
b0 ?
b0 /
b0 K
b0 %
b0 N
b0 0
b0 L
07
0>
08
0<
0:
06
b0 C
0=
0;
09
05
b0 B
b0 @
b0 1
b0 H
b0 2
b0 G
b0 A
b0 3
b0 I
b0 4
b0 R
b0 F
1!
#3000
b101000011000001000010011 "
b101000011000001000010011 '
0#
#4000
0!
#6000
1&
1.
b1101 D
b1101 J
b1101 Q
b1010 ?
b0 P
b1010 E
b1010 O
1)
b1010 /
b1010 K
b11 %
b11 N
b11 0
b11 L
17
b10011 C
1=
b10011 B
b1010 1
b1010 H
b11 2
b11 G
b100 3
b100 I
b10011 4
b101000011000001000010011 F
b0 R
1!
#8000
0!
#10000
b0 R
b1101 V
1!
#12000
0!
#14000
b0 R
b1101 V
1!
#15000
b110001010111001100010011 "
b110001010111001100010011 '
#16000
0!
#18000
b1000 D
b1000 J
b1000 Q
b10 P
b1100 E
b1100 O
b1100 /
b1100 K
b1010 %
b1010 N
b1010 0
b1010 L
b1100 ?
b1110010011 C
0=
1;
b1110010011 B
b1100 1
b1100 H
b1010 2
b1010 G
b111 A
b110 3
b110 I
b0 R
b1101 V
b110001010111001100010011 F
1!
#20000
0!
#22000
b0 R
b1000 X
1!
#24000
0!
#26000
b0 R
b1000 X
1!
#27000
b110001010110010000010011 "
b110001010110010000010011 '
#28000
0!
#30000
b1110 D
b1110 J
b1110 Q
b11 P
b1100010011 C
0;
19
b1100010011 B
b110 A
b1000 3
b1000 I
b110001010110010000010011 F
b0 R
b1000 X
1!
#32000
0!
#34000
b0 R
b1110 Z
1!
#36000
0!
#38000
b0 R
b1110 Z
1!
#39000
b110001010100001110010011 "
b110001010100001110010011 '
#40000
0!
#42000
b110 D
b110 J
b110 Q
b100 P
b1000010011 C
09
15
b1000010011 B
b100 A
b111 3
b111 I
b0 R
b1110 Z
b110001010100001110010011 F
1!
#44000
0!
#46000
b0 R
b110 Y
1!
#48000
0!
#50000
b0 R
b110 Y
1!
#52000
0!
#54000
b0 R
b110 Y
1!
